santacruz_watersmart/__init__.py
santacruz_watersmart/client.py
santacruz_watersmart/parsers.py
santacruz_watersmart/sqlite.py
santacruz_watersmart/storage_class.py
santacruz_watersmart-0.1.1.dist-info/LICENSE
santacruz_watersmart-0.1.1.dist-info/METADATA
santacruz_watersmart-0.1.1.dist-info/WHEEL
santacruz_watersmart-0.1.1.dist-info/top_level.txt
santacruz_watersmart-0.1.1.dist-info/RECORD
