Metadata-Version: 2.1
Name: santacruz-watersmart
Version: 0.1.1
Summary: Client to access the Santa Cruz Municipal Utilities water data
Home-page: https://github.com/streamnsight/santacruz-watersmart
Author: Emmanuel Leroy
Author-email: eleroy@msn.com
Project-URL: Bug Tracker, https://github.com/streamnsight/santacruz-watersmart/issues
Classifier: Programming Language :: Python :: 3
Classifier: License :: OSI Approved :: MIT License
Classifier: Operating System :: OS Independent
Requires-Python: >=3.9
License-File: LICENSE
Requires-Dist: httpx (<1,>=0.24.1)
